MANIFEST.in
README.rst
setup.py
happyml/__init__.py
happyml/datasets.py
happyml/models.py
happyml/plot.py
happyml/utils.py
happyml.egg-info/PKG-INFO
happyml.egg-info/SOURCES.txt
happyml.egg-info/dependency_links.txt
happyml.egg-info/not-zip-safe
happyml.egg-info/requires.txt
happyml.egg-info/top_level.txt
scripts/happy_data_creator
scripts/happy_gradient