Metadata-Version: 1.0
Name: happyml
Version: 0.0.5
Summary: Machine Learning library for educational purpose.
Home-page: https://github.com/guiferviz/happyml-py
Author: guiferviz
Author-email: guiferviz@gmail.com
License: MIT
Keywords: happy machine learning
Platform: UNKNOWN
